acp_python/__init__.py
acp_python/exceptions.py
acp_python/py.typed
acp_python/types.py
acp_python/agents/__init__.py
acp_python/agents/base.py
acp_python/agents/chat.py
acp_python/agents/user.py
acp_python/identity/README.md
acp_python/identity/__init__.py
acp_python/identity/types.py
acp_python/session/__init__.py
acp_python/session/policy.py
acp_python/session/store.py
acp_python/transport/__init__.py
acp_python/transport/base.py
acp_python/transport/nats.py
acp_python/utils/__init__.py
acp_python/utils/crypto.py
acp_python/utils/iter.py
acp_python-0.1.0.dist-info/METADATA
acp_python-0.1.0.dist-info/WHEEL
acp_python-0.1.0.dist-info/licenses/LICENSE
acp_python-0.1.0.dist-info/RECORD
